decoder_2_4.v
module decoder_2_4(E , In , Out);
input E;                            //宣告E為1bit的輸入埠
input [1:0] In;                     //宣告In為2bit的輸入埠
output [3:0]Out;                    //宣告Out為4bit的輸出埠
wire [3:0] Out;                     //宣告腳位資料型態  
assign Out = E ? 1'b1 << In : 4'h0; //如果E=1,Out = 0001 並左移In個位元
endmodule                           //如果E=0,不運作 Out全為0

decoder_3_8.v
module decode_3_8(E , In , Out);
input E;                                            //宣告E為1bit的輸入埠
input [2:0] In;                                     //宣告In為3bit的輸入埠
output [7:0] Out;                                   //宣告Out為8bit的輸出埠
wire E1 , G1 , G2;                                  //宣告三條接線E1,G1,G2                        
not u1(E1 , In[2]);                                 //定義E1 = IN[2]的反向
and a1(G1 , E , In[2]);                             //定義G1 = E & In[2]
and a2(G2 , E , E1);                                //定義G2 = E & E1
decoder_2_4 block1(G1 , In[1 : 0] , Out[7 : 4]);    //使用decoder_2_4 控制線為G1 輸入為In[1:0] 輸出為Out[7:4]
decoder_2_4 block2(G2 , In[1 : 0] , Out[3 : 0]);    //使用decoder_2_4 控制線為G2 輸入為In[1:0] 輸出為Out[3:0]
endmodule

decoder_3_8_tb.v
module decoder_3_8_tb;
reg E_tb;
reg [2:0] In_tb;
wire [7:0] Out_tb;
decode_3_8 decoder_1(.E(E_tb), .In(In_tb), .Out(Out_tb));

initial begin
    #0 E_tb = 0; In_tb = 3'b000;
    #10 E_tb = 1; In_tb = 3'b000;
    #10 E_tb = 1; In_tb = 3'b001;
    #10 E_tb = 1; In_tb = 3'b010;
    #10 E_tb = 1; In_tb = 3'b011;
    #10 E_tb = 1; In_tb = 3'b100;
    #10 E_tb = 1; In_tb = 3'b101;
    #10 E_tb = 1; In_tb = 3'b110;
    #10 E_tb = 1; In_tb = 3'b111;
    #10 $finish;
    end
initial
    begin
        $dumpfile("decoder.vcd");
        $dumpvars(0, decoder_1);
    end
endmodule

decoder.vcd
$date
	Wed Mar 23 18:28:11 2022
$end
$version
	Icarus Verilog
$end
$timescale
	1s
$end
$scope module decoder_3_8_tb $end
$scope module decoder_1 $end
$var wire 1 ! E $end
$var wire 1 " E1 $end
$var wire 1 # G1 $end
$var wire 1 $ G2 $end
$var wire 3 % In [2:0] $end
$var wire 8 & Out [7:0] $end
$scope module block1 $end
$var wire 1 # E $end
$var wire 2 ' In [1:0] $end
$var wire 4 ( Out [3:0] $end
$upscope $end
$scope module block2 $end
$var wire 1 $ E $end
$var wire 2 ) In [1:0] $end
$var wire 4 * Out [3:0] $end
$upscope $end
$upscope $end
$upscope $end
$enddefinitions $end
#0
$dumpvars
b0 *
b0 )
b0 (
b0 '
b0 &
b0 %
0$
0#
1"
0!
$end
#10
b1 &
b1 *
1$
1!
#20
b10 &
b10 *
b1 '
b1 )
b1 %
#30
b100 &
b100 *
b10 '
b10 )
b10 %
#40
b1000 &
b1000 *
b11 '
b11 )
b11 %
#50
0$
b1 (
0"
1#
b10000 &
b0 *
b0 '
b0 )
b100 %
#60
b100000 &
b10 (
b1 '
b1 )
b101 %
#70
b1000000 &
b100 (
b10 '
b10 )
b110 %
#80
b10000000 &
b1000 (
b11 '
b11 )
b111 %
